{
  "v1": {
    "enabled": true,
    "node": {
      "tag": "dev-48b1f20ca4aac12b41a33417841d91791601ebe5",
      "enabled": true
    },
    "python": {
      "tag": "",
      "enabled": false
    },
    "golang": {
      "tag": "",
      "enabled": false
    },
    "java": {
      "tag": "",
      "enabled": false
    }
  },
  "v1.1": {
    "enabled": false,
    "node": {
      "tag": "",
      "enabled": false
    },
    "python": {
      "tag": "",
      "enabled": false
    },
    "golang": {
      "tag": "",
      "enabled": false
    },
    "java": {
      "tag": "",
      "enabled": false
    }
  },
  "v2": {
    "enabled": false,
    "node": {
      "tag": "",
      "enabled": false
    },
    "python": {
      "tag": "",
      "enabled": false
    },
    "golang": {
      "tag": "",
      "enabled": false
    },
    "java": {
      "tag": "",
      "enabled": false
    }
  },
  "v3": {
    "enabled": false,
    "node": {
      "tag": "",
      "enabled": false
    },
    "python": {
      "tag": "",
      "enabled": false
    },
    "golang": {
      "tag": "",
      "enabled": false
    },
    "java": {
      "tag": "",
      "enabled": false
    }
  }
}